universal_data_connector/__init__.py
universal_data_connector/cli.py
universal_data_connector/connector.py
universal_data_connector/runner.py
universal_data_connector-0.1.1.dist-info/licenses/LICENSE.txt
universal_data_connector-0.1.1.dist-info/METADATA
universal_data_connector-0.1.1.dist-info/WHEEL
universal_data_connector-0.1.1.dist-info/entry_points.txt
universal_data_connector-0.1.1.dist-info/top_level.txt
universal_data_connector-0.1.1.dist-info/RECORD
