Metadata-Version: 2.4
Name: universal-data-connector
Version: 0.1.1
Summary: A Python package to query Oracle databases via CLI.
Author-email: Mhlasakululeka Mvubu <mhlavubu@woolworths.co.za>
Requires-Python: >=3.9
License-File: LICENSE.txt
Requires-Dist: click
Requires-Dist: pandas
Requires-Dist: oracledb
Requires-Dist: sqlalchemy
Dynamic: license-file
